pipereport/__init__.py
pipereport/base/__init__.py
pipereport/base/sink.py
pipereport/base/source.py
pipereport/base/templateregistry.py
pipereport/base/__pycache__/__init__.cpython-310.pyc
pipereport/base/__pycache__/connector.cpython-310.pyc
pipereport/base/__pycache__/sink.cpython-310.pyc
pipereport/base/__pycache__/source.cpython-310.pyc
pipereport/base/__pycache__/templateregistry.cpython-310.pyc
pipereport/runner/__init__.py
pipereport/runner/runner.py
pipereport/runner/__pycache__/__init__.cpython-310.pyc
pipereport/runner/__pycache__/runner.cpython-310.pyc
pipereport/sink/__init__.py
pipereport/sink/local.py
pipereport/sink/s3.py
pipereport/sink/__pycache__/__init__.cpython-310.pyc
pipereport/sink/__pycache__/local.cpython-310.pyc
pipereport/sink/__pycache__/s3.cpython-310.pyc
pipereport/telemetry/__init__.py
pipereport/telemetry/telemetry.py
pipereport/telemetry/__pycache__/__init__.cpython-310.pyc
pipereport/telemetry/__pycache__/telemetry.cpython-310.pyc
pipereport/template/__init__.py
pipereport/template/template.py
pipereport/template/__pycache__/__init__.cpython-310.pyc
pipereport/template/__pycache__/reader.cpython-310.pyc
pipereport/template/__pycache__/template.cpython-310.pyc
pipereport/template/registry/__init__.py
pipereport/template/registry/fs.py
pipereport/template/registry/gitfs.py
pipereport/template/registry/__pycache__/__init__.cpython-310.pyc
pipereport/template/registry/__pycache__/fs.cpython-310.pyc
pipereport/template/registry/__pycache__/gitfs.cpython-310.pyc
pipereport-0.0.10.dist-info/LICENSE
pipereport-0.0.10.dist-info/METADATA
pipereport-0.0.10.dist-info/WHEEL
pipereport-0.0.10.dist-info/top_level.txt
pipereport-0.0.10.dist-info/RECORD
