Metadata-Version: 2.1
Name: pipereport
Version: 0.0.10
Summary: A simple data pipeline management tool
Author-email: Nikolay Markov <enchantner@gmail.com>
License: Copyright (c) 2018 The Python Packaging Authority        
Project-URL: Homepage, https://github.com/enchantner/pipereport
Project-URL: Bug Tracker, https://github.com/enchantner/pipereport
Classifier: Programming Language :: Python :: 3
Classifier: License :: OSI Approved :: MIT License
Classifier: Operating System :: OS Independent
Requires-Python: >=3.7
License-File: LICENSE
Requires-Dist: boto3 (==1.24.68)
Requires-Dist: GitPython (==3.1.27)
Requires-Dist: PyYAML (==6.0)
